mlpcli/__init__.py
mlpcli/module_1.py
mlpcli/module_2.py
mlpcli/module_3.py
mlpcli/module_4.py
mlpcli/module_5.py
mlpcli-0.0.2.dist-info/METADATA
mlpcli-0.0.2.dist-info/WHEEL
mlpcli-0.0.2.dist-info/top_level.txt
mlpcli-0.0.2.dist-info/RECORD
